bosa_cli.cpython-311-x86_64-linux-gnu.so
bosa_cli.pyi
bosa_cli/__init__.pyi
bosa_cli/config.pyi
bosa_cli/constants.pyi
bosa_cli/main.pyi
bosa_cli/utils.pyi
bosa_cli/api/__init__.pyi
bosa_cli/api/auth.pyi
bosa_cli/api/base.pyi
bosa_cli/api/integrations.pyi
bosa_cli/api/models.pyi
bosa_cli/api/users.pyi
bosa_cli/commands/__init__.pyi
bosa_cli/commands/auth.pyi
bosa_cli/commands/base.pyi
bosa_cli/commands/integrations.pyi
bosa_cli/commands/users.pyi
bosa_cli.build/.gitignore
bosa_cli_binary-0.0.1.dist-info/METADATA
bosa_cli_binary-0.0.1.dist-info/WHEEL
bosa_cli_binary-0.0.1.dist-info/entry_points.txt
bosa_cli_binary-0.0.1.dist-info/top_level.txt
bosa_cli_binary-0.0.1.dist-info/RECORD
