Metadata-Version: 2.2
Name: bosa-cli-binary
Version: 0.0.1
Author-email: Bosa Engineers <bosa-eng@gdplabs.id>
Requires-Python: <3.14,>=3.11
Requires-Dist: requests<3.0.0,>=2.31.0
Requires-Dist: pydantic<3.0.0,>=2.11.7
Requires-Dist: auditwheel<7.0.0,>=6.4.2
Provides-Extra: dev
Requires-Dist: pytest>=8.4.1; extra == "dev"
Requires-Dist: pytest-cov>=6.2.1; extra == "dev"
Requires-Dist: ruff>=0.12.7; extra == "dev"
Requires-Dist: mypy>=1.17.0; extra == "dev"
Requires-Dist: pre-commit>=4.2.0; extra == "dev"
